LICENSE
README.md
setup.cfg
setup.py
src/djehouty/__init__.py
src/djehouty/ltz.py
src/djehouty/tcp.py
src/djehouty.egg-info/PKG-INFO
src/djehouty.egg-info/SOURCES.txt
src/djehouty.egg-info/dependency_links.txt
src/djehouty.egg-info/entry_points.txt
src/djehouty.egg-info/requires.txt
src/djehouty.egg-info/top_level.txt
src/djehouty.egg-info/zip-safe
src/djehouty/libgelf/__init__.py
src/djehouty/libgelf/formatters.py
src/djehouty/libgelf/handlers.py
src/djehouty/libltsv/__init__.py
src/djehouty/libltsv/adapters.py
src/djehouty/libltsv/formatters.py
src/djehouty/libltsv/handlers.py