Metadata-Version: 1.1
Name: djehouty
Version: 0.1.6
Summary: Djehouty intends to be a set of logging formatters and handlers to easily send log entries.
Home-page: https://github.com/ovh/djehouty
Author: Cedric DUMAY
Author-email: cedric.dumay@corp.ovh.com
License: BSD
Keywords: GELF,LTSV
Platform: UNKNOWN
Classifier: License :: OSI Approved :: BSD License
Classifier: Operating System :: POSIX
Classifier: Programming Language :: Python
Classifier: Programming Language :: Python :: 2
